pyladdersim/__init__.py
pyladdersim/components.py
pyladdersim/ladder.py
pyladdersim/sensors.py
pyladdersim/visualize_shapes.py
pyladdersim/visualizer.py
pyladdersim-0.1.0.dist-info/METADATA
pyladdersim-0.1.0.dist-info/WHEEL
pyladdersim-0.1.0.dist-info/top_level.txt
pyladdersim-0.1.0.dist-info/RECORD
