Metadata-Version: 2.1
Name: pyladdersim
Version: 0.1.0
Summary: An educational ladder logic simulator in Python
Home-page: https://github.com/akshatnerella/pyladdersim
Author: Akshat Nerella
Author-email: akshatnerella27@gmail.com
Classifier: Programming Language :: Python :: 3
Classifier: License :: OSI Approved :: MIT License
Classifier: Operating System :: OS Independent
Requires-Python: >=3.7
